wolfbet/__init__.py
wolfbet/core/__init__.py
wolfbet/core/Config.py
wolfbet/core/Connections.py
wolfbet/core/Constant.py
wolfbet/core/PPrint.py
wolfbet/core/Response.py
wolfbet/core/type.py
wolfbet/core/Utils.py
wolfbet-1.0.2.dist-info/WHEEL
wolfbet-1.0.2.dist-info/METADATA
wolfbet-1.0.2.dist-info/RECORD
